MANIFEST.in
setup.py
boilerplate_dcc_pyside_widget/__init__.py
boilerplate_dcc_pyside_widget/boilerplate_dcc_pyside_widget.py
boilerplate_dcc_pyside_widget.egg-info/PKG-INFO
boilerplate_dcc_pyside_widget.egg-info/SOURCES.txt
boilerplate_dcc_pyside_widget.egg-info/dependency_links.txt
boilerplate_dcc_pyside_widget.egg-info/not-zip-safe
boilerplate_dcc_pyside_widget.egg-info/top_level.txt
boilerplate_dcc_pyside_widget/lib/__init__.py
boilerplate_dcc_pyside_widget/lib/globals/__init__.py
boilerplate_dcc_pyside_widget/lib/globals/global_functions.py
boilerplate_dcc_pyside_widget/lib/globals/global_variables.py
boilerplate_dcc_pyside_widget/lib/gui/__init__.py
boilerplate_dcc_pyside_widget/lib/gui/dock_widget.py
boilerplate_dcc_pyside_widget/lib/gui/gui_functions.py
boilerplate_dcc_pyside_widget/lib/mvc/__init__.py
boilerplate_dcc_pyside_widget/lib/third_party/__init__.py
boilerplate_dcc_pyside_widget/lib/third_party/__init__.pyc
boilerplate_dcc_pyside_widget/lib/third_party/pysideuic/__init__.py
boilerplate_dcc_pyside_widget/lib/third_party/pysideuic/__init__.pyc
boilerplate_dcc_pyside_widget/lib/third_party/pysideuic/__init__.pyo
boilerplate_dcc_pyside_widget/lib/third_party/pysideuic/driver.py
boilerplate_dcc_pyside_widget/lib/third_party/pysideuic/driver.pyc
boilerplate_dcc_pyside_widget/lib/third_party/pysideuic/driver.pyo
boilerplate_dcc_pyside_widget/lib/third_party/pysideuic/exceptions.py
boilerplate_dcc_pyside_widget/lib/third_party/pysideuic/exceptions.pyc
boilerplate_dcc_pyside_widget/lib/third_party/pysideuic/exceptions.pyo
boilerplate_dcc_pyside_widget/lib/third_party/pysideuic/icon_cache.py
boilerplate_dcc_pyside_widget/lib/third_party/pysideuic/icon_cache.pyc
boilerplate_dcc_pyside_widget/lib/third_party/pysideuic/icon_cache.pyo
boilerplate_dcc_pyside_widget/lib/third_party/pysideuic/objcreator.py
boilerplate_dcc_pyside_widget/lib/third_party/pysideuic/objcreator.pyc
boilerplate_dcc_pyside_widget/lib/third_party/pysideuic/objcreator.pyo
boilerplate_dcc_pyside_widget/lib/third_party/pysideuic/properties.py
boilerplate_dcc_pyside_widget/lib/third_party/pysideuic/properties.pyc
boilerplate_dcc_pyside_widget/lib/third_party/pysideuic/properties.pyo
boilerplate_dcc_pyside_widget/lib/third_party/pysideuic/pyside-uic.1
