Metadata-Version: 1.0
Name: boilerplate-dcc-pyside-widget
Version: 0.0.5
Summary: Repository for boilerplate PySide DCC widget. This tool serves as barebone,      fully functional skeleton for DCC GUI tools written in PySide.
Home-page: http://timmwagener.com/
Author: Timm Wagener
Author-email: wagenertimm@gmail.com
License: MIT
Keywords: PySide DCC Maya Nuke Timm Wagener
Platform: UNKNOWN
Classifier: Programming Language :: Python
Classifier: Topic :: Software Development
